{
  "id": 1,
  "robots": [
    {"id": "larry-bird", "name": "Larry Bird"},
    {"id": "bbatc", "name": "BBATC"}
  ],
  "startingBaskets": ["magenta", "blue"],
  "isTieAllowed": true,
  "hasEnded": false,
  "rounds": [
    {
      "scores": [
        [
          {"time": 1767894863295, "isValid": true},
          {"time": 1767894891045, "isValid": true}
        ],
        [
          {"time": 1767894860930, "isValid": true},
          {"time": 1767894868177, "isValid": true},
          {"time": 1767894876901, "isValid": true},
          {"time": 1767894886654, "isValid": true},
          {"time": 1767894949351, "isValid": true}
        ]
      ],
      "fouls": [[], [{"time": 1767894908227, "isValid": true}]],
      "readyStates": [true, true],
      "baskets": ["magenta", "blue"],
      "hasEnded": true,
      "isConfirmed": true,
      "roundMaxLength": 60000,
      "runs": [
        {"startTime": 1767894845171, "endTime": 1767894899467},
        {"startTime": 1767894940729, "endTime": 1767894946477}
      ]
    },
    {
      "scores": [
        [
          {"time": 1767895052192, "isValid": true},
          {"time": 1767895058648, "isValid": true},
          {"time": 1767895066455, "isValid": true}
        ],
        []
      ],
      "fouls": [[{"time": 1767895091434, "isValid": true}], []],
      "readyStates": [false, false],
      "baskets": ["blue", "magenta"],
      "hasEnded": false,
      "isConfirmed": false,
      "roundMaxLength": 60000,
      "runs": [
        {"startTime": 1767895040602, "endTime": 1767895081624},
        {"startTime": 1767895084865, "endTime": 1767895087336}
      ]
    }
  ],
  "ballPlacement": [
    [0, 0],
    [1.52, 0.8],
    [-1.52, -0.8],
    [0.91, -1.04],
    [-0.91, 1.04],
    [-0.65, -0.04],
    [0.65, 0.04],
    [-0.22, -1.12],
    [0.22, 1.12],
    [-0.28, -0.2],
    [0.28, 0.2]
  ]
}